{
  "hash": "b28e6544",
  "browserHash": "0ffc8d5d",
  "optimized": {
    "vue": {
      "src": "../../../../node_modules/.pnpm/registry.npmmirror.com+vue@3.3.4/node_modules/vue/dist/vue.runtime.esm-browser.js",
      "file": "vue.js",
      "fileHash": "62aac45f",
      "needsInterop": false
    },
    "vitepress > @vue/devtools-api": {
      "src": "../../../../node_modules/.pnpm/registry.npmmirror.com+@vue+devtools-api@6.5.0/node_modules/@vue/devtools-api/lib/esm/index.js",
      "file": "vitepress___@vue_devtools-api.js",
      "fileHash": "9ec9b41a",
      "needsInterop": false
    }
  },
  "chunks": {}
}